akaidoo/__init__.py
akaidoo/banner.py
akaidoo/cli.py
akaidoo/config.py
akaidoo/context.py
akaidoo/main.py
akaidoo/scanner.py
akaidoo/server.py
akaidoo/service.py
akaidoo/shrinker.py
akaidoo/tree.py
akaidoo/types.py
akaidoo/utils.py
akaidoo-1.4.1.dist-info/licenses/LICENSE
akaidoo-1.4.1.dist-info/METADATA
akaidoo-1.4.1.dist-info/WHEEL
akaidoo-1.4.1.dist-info/entry_points.txt
akaidoo-1.4.1.dist-info/top_level.txt
akaidoo-1.4.1.dist-info/RECORD
