Metadata-Version: 2.4
Name: akaidoo
Version: 1.4.1
Summary: List files from Odoo addon dependencies using manifestoo.
License: MIT
Project-URL: Homepage, https://github.com/yourusername/akaidoo
Project-URL: Bug Tracker, https://github.com/yourusername/akaidoo/issues
Classifier: Development Status :: 3 - Alpha
Classifier: Intended Audience :: Developers
Classifier: Topic :: Software Development :: Build Tools
Classifier: License :: OSI Approved :: MIT License
Classifier: Programming Language :: Python :: 3
Classifier: Programming Language :: Python :: 3.8
Classifier: Programming Language :: Python :: 3.9
Classifier: Programming Language :: Python :: 3.10
Classifier: Programming Language :: Python :: 3.11
Classifier: Programming Language :: Python :: 3.12
Classifier: Operating System :: OS Independent
Requires-Python: >=3.8
License-File: LICENSE
Requires-Dist: manifestoo-core>=1.0.0
Requires-Dist: manifestoo
Requires-Dist: typer[all]>=0.9.0
Requires-Dist: pyperclip
Requires-Dist: tree-sitter
Requires-Dist: tree-sitter-python
Requires-Dist: GitPython
Provides-Extra: test
Requires-Dist: pytest; extra == "test"
Requires-Dist: pytest-mock; extra == "test"
Requires-Dist: typer[all]; extra == "test"
Provides-Extra: mcp
Requires-Dist: mcp; extra == "mcp"
Requires-Dist: fastmcp; extra == "mcp"
Dynamic: license-file
